wise/__init__.py
wise/apps.py
wise/models.py
wise/tasks.py
wise/urls.py
wise/dependencies/__init__.py
wise/dependencies/delphinus.py
wise/internal/__init__.py
wise/internal/health_check.py
wise/internal/views.py
wise/management/__init__.py
wise/management/commands/__init__.py
wise/management/commands/consume.py
wise/management/commands/export_periodic_tasks.py
wise/management/commands/health_check.py
wise/management/commands/serve_metrics.py
wise/management/commands/wise_setup.py
wise/migrations/__init__.py
wise/settings/__init__.py
wise/settings/dependencies.py
wise/settings/env.py
wise/settings/setup.py
wise/station/__init__.py
wise/station/consts.py
wise/station/heap.py
wise/station/publish.py
wise/station/registry.py
wise/station/updater.py
wise/station/views.py
wise/utils/__init__.py
wise/utils/async_redis.py
wise/utils/cache.py
wise/utils/candles.py
wise/utils/celery.py
wise/utils/django.py
wise/utils/exception.py
wise/utils/http.py
wise/utils/http_requests.py
wise/utils/kafka.py
wise/utils/models.py
wise/utils/monitoring.py
wise/utils/numbers.py
wise/utils/periodic_tasks.py
wise/utils/python.py
wise/utils/rate_limit.py
wise/utils/redis.py
wise/utils/secrets.py
wise/utils/sentry.py
wise/utils/stream_manager.py
wise/utils/time.py
wise/utils/tracing.py
wise/utils/formatters/__init__.py
wise/utils/formatters/number_formatter.py
wise/utils/metrics/__init__.py
wise/utils/metrics/logs.py
wise_app/__init__.py
wise_app/asgi.py
wise_app/env.py
wise_app/settings.py
wise_app/urls.py
wise_app/wsgi.py
wise_market/__init__.py
wise_market/admin.py
wise_market/apps.py
wise_market/models.py
wise_market/tests.py
wise_market/updaters.py
wise_market/utils.py
wise_market/views.py
wise_market/management/__init__.py
wise_market/management/commands/__init__.py
wise_market/management/commands/check_intial_models.py
wise_market/management/commands/remove_old_models.py
wise_market/management/commands/table_rename_migration.py
wise_market/management/commands/utils.py
wiselib-0.3.33.dist-info/METADATA
wiselib-0.3.33.dist-info/WHEEL
wiselib-0.3.33.dist-info/top_level.txt
wiselib-0.3.33.dist-info/RECORD
