Metadata-Version: 2.1
Name: wiselib
Version: 0.3.33
Summary: WISE Library
Home-page: https://github.com/yourusername/wiselib
Author: Wise Man
Author-email: your.email@example.com
Classifier: Programming Language :: Python :: 3
Classifier: License :: OSI Approved :: MIT License
Classifier: Operating System :: OS Independent
Requires-Python: >=3.6
Requires-Dist: setuptools >=70.3.0
Requires-Dist: Django >=4.0.0
Requires-Dist: django-prometheus ==2.3.1
Requires-Dist: celery ==5.4.0
Requires-Dist: django-celery-results ~=2.5.1
Requires-Dist: django-celery-beat ~=2.5.0
Requires-Dist: requests
Requires-Dist: redis ~=5.0.4
Requires-Dist: djangorestframework
Requires-Dist: urllib3 ~=2.2.2
Requires-Dist: pydantic >=2.7.4
Requires-Dist: kafka-python ~=2.0.2
Requires-Dist: opentelemetry-api >=1.24.0
Requires-Dist: opentelemetry-sdk >=1.24.0
Requires-Dist: opentelemetry-exporter-otlp-proto-common >=1.24.0
Requires-Dist: opentelemetry-exporter-otlp-proto-http >=1.24.0
Requires-Dist: boto3 >=1.34.133
Requires-Dist: sentry-sdk >=1.45.1
Requires-Dist: pydantic-settings
Requires-Dist: deprecated
